dpm_toolkit/__init__.py
dpm_toolkit/__main__.py
dpm_toolkit/cli.py
dpm_toolkit/py.typed
dpm_toolkit-2025.8.14.dist-info/WHEEL
dpm_toolkit-2025.8.14.dist-info/entry_points.txt
dpm_toolkit-2025.8.14.dist-info/METADATA
dpm_toolkit-2025.8.14.dist-info/RECORD
