Metadata-Version: 2.3
Name: dpm-toolkit
Version: 2025.8.14
Summary: Open-source tools and models for working with DPM databases
Author: Jim Lundin
Author-email: Jim Lundin <jimeriklundin@gmail.com>
License: MIT License
Requires-Dist: archive
Requires-Dist: pyyaml>=6.0.2
Requires-Dist: migrate ; extra == 'migrate'
Requires-Dist: schema ; extra == 'schema'
Requires-Dist: scrape ; extra == 'scrape'
Requires-Python: >=3.13
Provides-Extra: migrate
Provides-Extra: schema
Provides-Extra: scrape
